simprad/__init__.py
simprad/__main__.py
simprad-1.0.7.dist-info/LICENSE
simprad-1.0.7.dist-info/METADATA
simprad-1.0.7.dist-info/WHEEL
simprad-1.0.7.dist-info/top_level.txt
simprad-1.0.7.dist-info/RECORD
