Metadata-Version: 2.1
Name: simprad
Version: 1.0.7
Summary: Simplify radicals.
Home-page: https://github.com/the-garlic-os/simprad
Author: garlicOS®
Author-email: sisdfk@gmail.com
License: UNKNOWN
Platform: UNKNOWN
Classifier: Programming Language :: Python :: 3
Classifier: License :: OSI Approved :: The Unlicense (Unlicense)
Classifier: Operating System :: OS Independent
Requires-Python: >=3.6
